errno2/__init__.py
errno2/py.typed
errno2-0.0.4.dist-info/METADATA
errno2-0.0.4.dist-info/WHEEL
errno2-0.0.4.dist-info/licenses/LICENSE
errno2-0.0.4.dist-info/RECORD
